program_searcher/__init__.py
program_searcher/evolution_operator.py
program_searcher/exceptions.py
program_searcher/history_tracker.py
program_searcher/mutation_strategy.py
program_searcher/program_model.py
program_searcher/program_search.py
program_searcher/stop_condition.py
program_searcher-0.1.1.dev0.dist-info/METADATA
program_searcher-0.1.1.dev0.dist-info/WHEEL
program_searcher-0.1.1.dev0.dist-info/RECORD
