Metadata-Version: 2.3
Name: program-searcher
Version: 0.1.1.dev0
Summary: 
Author: jerzyb
Author-email: devjerzy@gmail.com
Requires-Python: >=3.11,<4.0
Classifier: Programming Language :: Python :: 3
Classifier: Programming Language :: Python :: 3.11
Classifier: Programming Language :: Python :: 3.12
Classifier: Programming Language :: Python :: 3.13
Requires-Dist: networkx (>=3.5,<4.0)
Requires-Dist: typing-extensions (>=4.14.1,<5.0.0)
